jinja2_jsonschema/__init__.py
jinja2_jsonschema/errors.py
jinja2_jsonschema/extension.py
jinja2_jsonschema/py.typed
jinja2_jsonschema-0.3.0.dist-info/METADATA
jinja2_jsonschema-0.3.0.dist-info/WHEEL
jinja2_jsonschema-0.3.0.dist-info/licenses/LICENSE
jinja2_jsonschema-0.3.0.dist-info/RECORD
