Metadata-Version: 2.3
Name: jinja2-jsonschema
Version: 0.3.0
Summary: JSON/YAML schema validation within Jinja2 templates
Project-URL: Homepage, https://github.com/copier-org/jinja2-jsonschema
Project-URL: Repository, https://github.com/copier-org/jinja2-jsonschema
Author-email: Sigurd Spieckermann <sigurd.spieckermann@gmail.com>
License: MIT
License-File: LICENSE
Keywords: extension,jinja,jinja2,json,jsonschema,yaml
Classifier: Development Status :: 4 - Beta
Classifier: Intended Audience :: Developers
Classifier: License :: OSI Approved :: MIT License
Classifier: Operating System :: OS Independent
Classifier: Programming Language :: Python
Classifier: Programming Language :: Python :: 3
Classifier: Programming Language :: Python :: 3.9
Classifier: Programming Language :: Python :: 3.10
Classifier: Programming Language :: Python :: 3.11
Classifier: Programming Language :: Python :: 3.12
Classifier: Programming Language :: Python :: 3.13
Requires-Python: >=3.9
Requires-Dist: jinja2>=3.0.0
Requires-Dist: jsonschema>=4.18.0
Requires-Dist: referencing>=0.28.4
Provides-Extra: yaml
Requires-Dist: pyyaml>=6.0.0; extra == 'yaml'
